mudssky_pyutils-0.3.0.dist-info/licenses/AUTHORS.rst
mudssky_pyutils-0.3.0.dist-info/licenses/LICENSE
pyutils/__init__.py
pyutils/array.py
pyutils/async_utils.py
pyutils/bytes.py
pyutils/cli.py
pyutils/collection.py
pyutils/date.py
pyutils/encoding.py
pyutils/function.py
pyutils/math.py
pyutils/object.py
pyutils/pyutils.py
pyutils/string.py
pyutils/type_utils.py
pyutils/url.py
mudssky_pyutils-0.3.0.dist-info/METADATA
mudssky_pyutils-0.3.0.dist-info/WHEEL
mudssky_pyutils-0.3.0.dist-info/top_level.txt
mudssky_pyutils-0.3.0.dist-info/RECORD
