Metadata-Version: 2.4
Name: mudssky-pyutils
Version: 0.3.0
Summary: Python通用工具库 - 提供丰富的实用函数和工具类
Author-email: mudssky <mudssky@gmail.com>
Maintainer-email: mudssky <mudssky@gmail.com>
License-Expression: MIT
Project-URL: bugs, https://github.com/mudssky/pyutils/issues
Project-URL: changelog, https://github.com/mudssky/pyutils/blob/master/changelog.md
Project-URL: homepage, https://github.com/mudssky/pyutils
Keywords: utils,utilities,tools,helpers
Classifier: Development Status :: 4 - Beta
Classifier: Intended Audience :: Developers
Classifier: Programming Language :: Python :: 3
Classifier: Programming Language :: Python :: 3.10
Classifier: Programming Language :: Python :: 3.11
Classifier: Programming Language :: Python :: 3.12
Classifier: Programming Language :: Python :: 3.13
Classifier: Programming Language :: Python :: 3.14
Requires-Python: >=3.10
License-File: LICENSE
License-File: AUTHORS.rst
Requires-Dist: typer
Dynamic: license-file
